{
  "data": {
    "dataset": "2-083-219",
    "POI_id": "561647",
    "travelType": "음식점",
    "place": "식껍 발산점",
    "area": "서울"
  },
  "imageInfo": [
    {
      "image_id": 0,
      "filename": "561647_0_su_5_식껍 발산점_1_001.png",
      "mapx": 37.5600926354663,
      "mapy": 126.838304106686,
      "width": 3840,
      "height": 2160,
      "caption_info": [
        "식껍 발산점(마곡동)",
        "간판, 여닫이문"
      ]
    },
    {
      "image_id": 1,
      "filename": "561647_0_su_5_식껍 발산점_1_002.png",
      "mapx": 37.5600926354663,
      "mapy": 126.838304106686,
      "width": 3840,
      "height": 2160,
      "caption_info": [
        "식껍 발산점(마곡동)",
        "간판"
      ]
    },
    {
      "image_id": 2,
      "filename": "561647_0_su_5_식껍 발산점_1_003.png",
      "mapx": 37.5600926354663,
      "mapy": 126.838304106686,
      "width": 3840,
      "height": 2160,
      "caption_info": [
        "식껍 발산점(마곡동)",
        "에어컨, 메뉴판"
      ]
    },
    {
      "image_id": 3,
      "filename": "561647_0_su_5_식껍 발산점_1_004.png",
      "mapx": 37.5600926354663,
      "mapy": 126.838304106686,
      "width": 3840,
      "height": 2160,
      "caption_info": [
        "식껍 발산점(마곡동)",
        "메뉴판"
      ]
    },
    {
      "image_id": 4,
      "filename": "561647_0_su_5_식껍 발산점_1_005.png",
      "mapx": 37.5600926354663,
      "mapy": 126.838304106686,
      "width": 3840,
      "height": 2160,
      "caption_info": [
        "식껍 발산점(마곡동)",
        "껍데기"
      ]
    }
  ],
  "annotations": [
    {
      "image_id": 0,
      "question": [
        {
          "question_id": 0,
          "question_type": "정보",
          "question": "영업시간은 어떻게 되나요?",
          "question_wordNum": 3,
          "answer": "00:00~24:00",
          "answer_wordNum": 1,
          "fact": [
            "식껍 발산점,영업시간,00:00~24:00"
          ]
        },
        {
          "question_id": 1,
          "question_type": "관계",
          "question": "이 곳에 인접한 시설이 있나요?",
          "question_wordNum": 5,
          "answer": "발산역 2번 출구, 머구리, 마곡집",
          "answer_wordNum": 5,
          "fact": [
            "식껍 발산점,인접,발산역 2번 출구, 머구리, 마곡집"
          ]
        },
        {
          "question_id": 2,
          "question_type": "정보",
          "question": "이 곳의 주소는 어떻게 되나요?",
          "question_wordNum": 5,
          "answer": "서울 강서구 강서로 385 SB타워 1층 125호 126호",
          "answer_wordNum": 8,
          "fact": [
            "식껍 발산점,주소,서울 강서구 강서로 385 SB타워 1층 125호 126호"
          ]
        },
        {
          "question_id": 3,
          "question_type": "정보",
          "question": "연락처가 어떻게 되나요?",
          "question_wordNum": 3,
          "answer": "02-2659-1992",
          "answer_wordNum": 1,
          "fact": [
            "식껍 발산점,연락처,02-2659-1992"
          ]
        }
      ]
    },
    {
      "image_id": 1,
      "question": [
        {
          "question_id": 0,
          "question_type": "정보",
          "question": "휴무일을 알 수 있나요?",
          "question_wordNum": 4,
          "answer": "알수없음",
          "answer_wordNum": 1,
          "fact": [
            "식껍 발산점,휴무일,알수없음"
          ]
        },
        {
          "question_id": 1,
          "question_type": "정보",
          "question": "이 곳의 주요 메뉴는 무엇이 있나요?",
          "question_wordNum": 6,
          "answer": "생고기모듬, 숯불쭈꾸미",
          "answer_wordNum": 2,
          "fact": [
            "식껍 발산점,메뉴,생고기모듬, 숯불쭈꾸미"
          ]
        },
        {
          "question_id": 2,
          "question_type": "탐색",
          "question": "주차시설이 있나요?",
          "question_wordNum": 2,
          "answer": "있음",
          "answer_wordNum": 1,
          "fact": [
            "식껍 발산점,주차시설,있음"
          ]
        },
        {
          "question_id": 3,
          "question_type": "정보",
          "question": "이 곳의 주소는 어떻게 되나요?",
          "question_wordNum": 5,
          "answer": "서울 강서구 강서로 385 SB타워 1층 125호 126호",
          "answer_wordNum": 8,
          "fact": [
            "식껍 발산점,주소,서울 강서구 강서로 385 SB타워 1층 125호 126호"
          ]
        }
      ]
    },
    {
      "image_id": 2,
      "question": [
        {
          "question_id": 0,
          "question_type": "관계",
          "question": "이 곳에 인접한 시설이 있나요?",
          "question_wordNum": 5,
          "answer": "발산역 2번 출구, 머구리, 마곡집",
          "answer_wordNum": 5,
          "fact": [
            "식껍 발산점,인접,발산역 2번 출구, 머구리, 마곡집"
          ]
        },
        {
          "question_id": 1,
          "question_type": "정보",
          "question": "연락처가 어떻게 되나요?",
          "question_wordNum": 3,
          "answer": "02-2659-1992",
          "answer_wordNum": 1,
          "fact": [
            "식껍 발산점,연락처,02-2659-1992"
          ]
        },
        {
          "question_id": 2,
          "question_type": "정보",
          "question": "영업시간은 어떻게 되나요?",
          "question_wordNum": 3,
          "answer": "00:00~24:00",
          "answer_wordNum": 1,
          "fact": [
            "식껍 발산점,영업시간,00:00~24:00"
          ]
        },
        {
          "question_id": 3,
          "question_type": "정보",
          "question": "휴무일을 알 수 있나요?",
          "question_wordNum": 4,
          "answer": "알수없음",
          "answer_wordNum": 1,
          "fact": [
            "식껍 발산점,휴무일,알수없음"
          ]
        }
      ]
    },
    {
      "image_id": 3,
      "question": [
        {
          "question_id": 0,
          "question_type": "정보",
          "question": "휴무일을 알 수 있나요?",
          "question_wordNum": 4,
          "answer": "알수없음",
          "answer_wordNum": 1,
          "fact": [
            "식껍 발산점,휴무일,알수없음"
          ]
        },
        {
          "question_id": 1,
          "question_type": "정보",
          "question": "연락처가 어떻게 되나요?",
          "question_wordNum": 3,
          "answer": "02-2659-1992",
          "answer_wordNum": 1,
          "fact": [
            "식껍 발산점,연락처,02-2659-1992"
          ]
        },
        {
          "question_id": 2,
          "question_type": "정보",
          "question": "영업시간은 어떻게 되나요?",
          "question_wordNum": 3,
          "answer": "00:00~24:00",
          "answer_wordNum": 1,
          "fact": [
            "식껍 발산점,영업시간,00:00~24:00"
          ]
        },
        {
          "question_id": 3,
          "question_type": "정보",
          "question": "이 곳의 주요 메뉴는 무엇이 있나요?",
          "question_wordNum": 6,
          "answer": "생고기모듬, 숯불쭈꾸미",
          "answer_wordNum": 2,
          "fact": [
            "식껍 발산점,메뉴,생고기모듬, 숯불쭈꾸미"
          ]
        }
      ]
    },
    {
      "image_id": 4,
      "question": [
        {
          "question_id": 0,
          "question_type": "관계",
          "question": "이 곳에 인접한 시설이 있나요?",
          "question_wordNum": 5,
          "answer": "발산역 2번 출구, 머구리, 마곡집",
          "answer_wordNum": 5,
          "fact": [
            "식껍 발산점,인접,발산역 2번 출구, 머구리, 마곡집"
          ]
        },
        {
          "question_id": 1,
          "question_type": "정보",
          "question": "영업시간은 어떻게 되나요?",
          "question_wordNum": 3,
          "answer": "00:00~24:00",
          "answer_wordNum": 1,
          "fact": [
            "식껍 발산점,영업시간,00:00~24:00"
          ]
        },
        {
          "question_id": 2,
          "question_type": "정보",
          "question": "연락처가 어떻게 되나요?",
          "question_wordNum": 3,
          "answer": "02-2659-1992",
          "answer_wordNum": 1,
          "fact": [
            "식껍 발산점,연락처,02-2659-1992"
          ]
        },
        {
          "question_id": 3,
          "question_type": "정보",
          "question": "이 곳의 주요 메뉴는 무엇이 있나요?",
          "question_wordNum": 6,
          "answer": "생고기모듬, 숯불쭈꾸미",
          "answer_wordNum": 2,
          "fact": [
            "식껍 발산점,메뉴,생고기모듬, 숯불쭈꾸미"
          ]
        }
      ]
    }
  ]
}