{
  "data": {
    "dataset": "2-083-219",
    "POI_id": "559218",
    "travelType": "음식점",
    "place": "롯데리아 상계점",
    "area": "서울"
  },
  "imageInfo": [
    {
      "image_id": 0,
      "filename": "559218_0_su_5_롯데리아 상계점_1_001.png",
      "mapx": 37.6583977301857,
      "mapy": 127.073988938422,
      "width": 3840,
      "height": 2160,
      "caption_info": [
        "롯데리아 상계점(노원구)",
        "간판, 유리창"
      ]
    },
    {
      "image_id": 1,
      "filename": "559218_0_su_5_롯데리아 상계점_1_002.png",
      "mapx": 37.6583977301857,
      "mapy": 127.073988938422,
      "width": 3840,
      "height": 2160,
      "caption_info": [
        "롯데리아 상계점(노원구)",
        "간판, 유리창"
      ]
    },
    {
      "image_id": 2,
      "filename": "559218_0_su_5_롯데리아 상계점_1_003.png",
      "mapx": 37.6583977301857,
      "mapy": 127.073988938422,
      "width": 3840,
      "height": 2160,
      "caption_info": [
        "롯데리아 상계점(노원구)",
        "테이블, 등받이 의자"
      ]
    },
    {
      "image_id": 3,
      "filename": "559218_0_su_5_롯데리아 상계점_1_004.png",
      "mapx": 37.6583977301857,
      "mapy": 127.073988938422,
      "width": 3840,
      "height": 2160,
      "caption_info": [
        "롯데리아 상계점(노원구)",
        "메뉴판"
      ]
    },
    {
      "image_id": 4,
      "filename": "559218_0_su_5_롯데리아 상계점_1_005.png",
      "mapx": 37.6583977301857,
      "mapy": 127.073988938422,
      "width": 3840,
      "height": 2160,
      "caption_info": [
        "롯데리아 상계점(노원구)",
        "햄버거"
      ]
    }
  ],
  "annotations": [
    {
      "image_id": 0,
      "question": [
        {
          "question_id": 0,
          "question_type": "탐색",
          "question": "주차시설이 있는지 알 수 있나요?",
          "question_wordNum": 5,
          "answer": "있음",
          "answer_wordNum": 1,
          "fact": [
            "롯데리아 상계점,주차시설,있음"
          ]
        },
        {
          "question_id": 1,
          "question_type": "정보",
          "question": "영업시간은 어떻게 되나요?",
          "question_wordNum": 3,
          "answer": "10:00-23:00",
          "answer_wordNum": 1,
          "fact": [
            "롯데리아 상계점,영업시간,10:00-23:00"
          ]
        },
        {
          "question_id": 2,
          "question_type": "정보",
          "question": "휴무일은 어떻게 되나요?",
          "question_wordNum": 3,
          "answer": "없음",
          "answer_wordNum": 1,
          "fact": [
            "롯데리아 상계점,휴무일,없음"
          ]
        },
        {
          "question_id": 3,
          "question_type": "관계",
          "question": "이 곳에 인접한 시설을 알 수 있나요?",
          "question_wordNum": 7,
          "answer": "상계역 1번 출구, 파리바게뜨, 떡낙원",
          "answer_wordNum": 5,
          "fact": [
            "롯데리아 상계점,인접,상계역 1번 출구, 파리바게뜨, 떡낙원"
          ]
        }
      ]
    },
    {
      "image_id": 1,
      "question": [
        {
          "question_id": 0,
          "question_type": "탐색",
          "question": "주차시설이 있는지 알 수 있나요?",
          "question_wordNum": 5,
          "answer": "있음",
          "answer_wordNum": 1,
          "fact": [
            "롯데리아 상계점,주차시설,있음"
          ]
        },
        {
          "question_id": 1,
          "question_type": "정보",
          "question": "이 곳의 주소를 알 수 있나요?",
          "question_wordNum": 6,
          "answer": "서울 노원구 한글비석로 369",
          "answer_wordNum": 4,
          "fact": [
            "롯데리아 상계점,주소,서울 노원구 한글비석로 369"
          ]
        },
        {
          "question_id": 2,
          "question_type": "정보",
          "question": "영업시간은 어떻게 되나요?",
          "question_wordNum": 3,
          "answer": "10:00-23:00",
          "answer_wordNum": 1,
          "fact": [
            "롯데리아 상계점,영업시간,10:00-23:00"
          ]
        },
        {
          "question_id": 3,
          "question_type": "관계",
          "question": "이 곳에 인접한 시설이 있나요?",
          "question_wordNum": 5,
          "answer": "상계역 1번 출구, 파리바게뜨, 떡낙원",
          "answer_wordNum": 5,
          "fact": [
            "롯데리아 상계점,인접,상계역 1번 출구, 파리바게뜨, 떡낙원"
          ]
        }
      ]
    },
    {
      "image_id": 2,
      "question": [
        {
          "question_id": 0,
          "question_type": "정보",
          "question": "영업시간을 알 수 있나요?",
          "question_wordNum": 4,
          "answer": "10:00-23:00",
          "answer_wordNum": 1,
          "fact": [
            "롯데리아 상계점,영업시간,10:00-23:00"
          ]
        },
        {
          "question_id": 1,
          "question_type": "정보",
          "question": "대표 메뉴가 무엇인가요?",
          "question_wordNum": 3,
          "answer": "한우불고기버거, 새우버거",
          "answer_wordNum": 2,
          "fact": [
            "롯데리아 상계점,메뉴,한우불고기버거, 새우버거"
          ]
        },
        {
          "question_id": 2,
          "question_type": "탐색",
          "question": "주차시설이 있나요?",
          "question_wordNum": 2,
          "answer": "있음",
          "answer_wordNum": 1,
          "fact": [
            "롯데리아 상계점,주차시설,있음"
          ]
        },
        {
          "question_id": 3,
          "question_type": "정보",
          "question": "휴무일은 어떻게 되나요?",
          "question_wordNum": 3,
          "answer": "없음",
          "answer_wordNum": 1,
          "fact": [
            "롯데리아 상계점,휴무일,없음"
          ]
        }
      ]
    },
    {
      "image_id": 3,
      "question": [
        {
          "question_id": 0,
          "question_type": "정보",
          "question": "대표 메뉴가 무엇인가요?",
          "question_wordNum": 3,
          "answer": "한우불고기버거, 새우버거",
          "answer_wordNum": 2,
          "fact": [
            "롯데리아 상계점,메뉴,한우불고기버거, 새우버거"
          ]
        },
        {
          "question_id": 1,
          "question_type": "탐색",
          "question": "주차시설이 있는지 알 수 있나요?",
          "question_wordNum": 5,
          "answer": "있음",
          "answer_wordNum": 1,
          "fact": [
            "롯데리아 상계점,주차시설,있음"
          ]
        },
        {
          "question_id": 2,
          "question_type": "관계",
          "question": "이 곳에 인접한 시설이 있나요?",
          "question_wordNum": 5,
          "answer": "상계역 1번 출구, 파리바게뜨, 떡낙원",
          "answer_wordNum": 5,
          "fact": [
            "롯데리아 상계점,인접,상계역 1번 출구, 파리바게뜨, 떡낙원"
          ]
        },
        {
          "question_id": 3,
          "question_type": "정보",
          "question": "연락처를 알 수 있나요?",
          "question_wordNum": 4,
          "answer": "02-930-9912",
          "answer_wordNum": 1,
          "fact": [
            "롯데리아 상계점,연락처,02-930-9912"
          ]
        }
      ]
    },
    {
      "image_id": 4,
      "question": [
        {
          "question_id": 0,
          "question_type": "정보",
          "question": "영업시간을 알 수 있나요?",
          "question_wordNum": 4,
          "answer": "10:00-23:00",
          "answer_wordNum": 1,
          "fact": [
            "롯데리아 상계점,영업시간,10:00-23:00"
          ]
        },
        {
          "question_id": 1,
          "question_type": "정보",
          "question": "연락처가 어떻게 되나요?",
          "question_wordNum": 3,
          "answer": "02-930-9912",
          "answer_wordNum": 1,
          "fact": [
            "롯데리아 상계점,연락처,02-930-9912"
          ]
        },
        {
          "question_id": 2,
          "question_type": "정보",
          "question": "이 곳의 주소를 알 수 있나요?",
          "question_wordNum": 6,
          "answer": "서울 노원구 한글비석로 369",
          "answer_wordNum": 4,
          "fact": [
            "롯데리아 상계점,주소,서울 노원구 한글비석로 369"
          ]
        },
        {
          "question_id": 3,
          "question_type": "관계",
          "question": "이 곳에 인접한 시설이 있나요?",
          "question_wordNum": 5,
          "answer": "상계역 1번 출구, 파리바게뜨, 떡낙원",
          "answer_wordNum": 5,
          "fact": [
            "롯데리아 상계점,인접,상계역 1번 출구, 파리바게뜨, 떡낙원"
          ]
        }
      ]
    }
  ]
}