{
  "data": {
    "dataset": "2-083-219",
    "POI_id": "564283",
    "travelType": "음식점",
    "place": "세라즈피자펍",
    "area": "서울"
  },
  "imageInfo": [
    {
      "image_id": 0,
      "filename": "564283_0_su_5_세라즈피자펍_1_001.png",
      "mapx": 37.479966429878,
      "mapy": 126.88263620024,
      "width": 3840,
      "height": 2160,
      "caption_info": [
        "세라즈피자펍(가산동)",
        "간판"
      ]
    },
    {
      "image_id": 1,
      "filename": "564283_0_su_5_세라즈피자펍_1_002.png",
      "mapx": 37.479966429878,
      "mapy": 126.88263620024,
      "width": 3840,
      "height": 2160,
      "caption_info": [
        "세라즈피자펍(가산동)",
        "간판"
      ]
    },
    {
      "image_id": 2,
      "filename": "564283_0_su_5_세라즈피자펍_1_003.png",
      "mapx": 37.479966429878,
      "mapy": 126.88263620024,
      "width": 3840,
      "height": 2160,
      "caption_info": [
        "세라즈피자펍(가산동)",
        "테이블, 의자"
      ]
    },
    {
      "image_id": 3,
      "filename": "564283_0_su_5_세라즈피자펍_1_004.png",
      "mapx": 37.479966429878,
      "mapy": 126.88263620024,
      "width": 3840,
      "height": 2160,
      "caption_info": [
        "세라즈피자펍(가산동)",
        "메뉴판"
      ]
    },
    {
      "image_id": 4,
      "filename": "564283_0_su_5_세라즈피자펍_1_005.png",
      "mapx": 37.479966429878,
      "mapy": 126.88263620024,
      "width": 3840,
      "height": 2160,
      "caption_info": [
        "세라즈피자펍(가산동)",
        "피자, 파스타, 샐러드"
      ]
    }
  ],
  "annotations": [
    {
      "image_id": 0,
      "question": [
        {
          "question_id": 0,
          "question_type": "정보",
          "question": "이 곳의 주소를 알 수 있나요?",
          "question_wordNum": 6,
          "answer": "서울 금천구 가산디지털1로 168 A동 2층 222호",
          "answer_wordNum": 7,
          "fact": [
            "세라즈피자펍,주소,서울 금천구 가산디지털1로 168 A동 2층 222호"
          ]
        },
        {
          "question_id": 1,
          "question_type": "탐색",
          "question": "주차시설이 있나요?",
          "question_wordNum": 2,
          "answer": "있음",
          "answer_wordNum": 1,
          "fact": [
            "세라즈피자펍,주차시설,있음"
          ]
        },
        {
          "question_id": 2,
          "question_type": "정보",
          "question": "이 곳의 대표적인 메뉴를 알 수 있나요?",
          "question_wordNum": 7,
          "answer": "피자, 국내 수제맥주",
          "answer_wordNum": 3,
          "fact": [
            "세라즈피자펍,메뉴,피자, 국내 수제맥주"
          ]
        },
        {
          "question_id": 3,
          "question_type": "정보",
          "question": "휴무일은 어떻게 되나요?",
          "question_wordNum": 3,
          "answer": "매주 토요일, 일요일",
          "answer_wordNum": 3,
          "fact": [
            "세라즈피자펍,휴무일,매주 토요일, 일요일"
          ]
        }
      ]
    },
    {
      "image_id": 1,
      "question": [
        {
          "question_id": 0,
          "question_type": "정보",
          "question": "휴무일은 어떻게 되나요?",
          "question_wordNum": 3,
          "answer": "매주 토요일, 일요일",
          "answer_wordNum": 3,
          "fact": [
            "세라즈피자펍,휴무일,매주 토요일, 일요일"
          ]
        },
        {
          "question_id": 1,
          "question_type": "관계",
          "question": "이 곳에 인접한 시설을 알 수 있나요?",
          "question_wordNum": 7,
          "answer": "가산디지털단지역 6번 출구, 여기다도매, 홍삼명가",
          "answer_wordNum": 5,
          "fact": [
            "세라즈피자펍,인접,가산디지털단지역 6번 출구, 여기다도매, 홍삼명가"
          ]
        },
        {
          "question_id": 2,
          "question_type": "정보",
          "question": "이 곳의 주소는 어떻게 되나요?",
          "question_wordNum": 5,
          "answer": "서울 금천구 가산디지털1로 168 A동 2층 222호",
          "answer_wordNum": 7,
          "fact": [
            "세라즈피자펍,주소,서울 금천구 가산디지털1로 168 A동 2층 222호"
          ]
        },
        {
          "question_id": 3,
          "question_type": "정보",
          "question": "연락처가 어떻게 되나요?",
          "question_wordNum": 3,
          "answer": "0507-1379-0415",
          "answer_wordNum": 1,
          "fact": [
            "세라즈피자펍,연락처,0507-1379-0415"
          ]
        }
      ]
    },
    {
      "image_id": 2,
      "question": [
        {
          "question_id": 0,
          "question_type": "정보",
          "question": "휴무일은 어떻게 되나요?",
          "question_wordNum": 3,
          "answer": "매주 토요일, 일요일",
          "answer_wordNum": 3,
          "fact": [
            "세라즈피자펍,휴무일,매주 토요일, 일요일"
          ]
        },
        {
          "question_id": 1,
          "question_type": "관계",
          "question": "이 곳에 인접한 시설을 알 수 있나요?",
          "question_wordNum": 7,
          "answer": "가산디지털단지역 6번 출구, 여기다도매, 홍삼명가",
          "answer_wordNum": 5,
          "fact": [
            "세라즈피자펍,인접,가산디지털단지역 6번 출구, 여기다도매, 홍삼명가"
          ]
        },
        {
          "question_id": 2,
          "question_type": "정보",
          "question": "연락처를 알 수 있나요?",
          "question_wordNum": 4,
          "answer": "0507-1379-0415",
          "answer_wordNum": 1,
          "fact": [
            "세라즈피자펍,연락처,0507-1379-0415"
          ]
        },
        {
          "question_id": 3,
          "question_type": "정보",
          "question": "이 곳의 주소를 알 수 있나요?",
          "question_wordNum": 6,
          "answer": "서울 금천구 가산디지털1로 168 A동 2층 222호",
          "answer_wordNum": 7,
          "fact": [
            "세라즈피자펍,주소,서울 금천구 가산디지털1로 168 A동 2층 222호"
          ]
        }
      ]
    },
    {
      "image_id": 3,
      "question": [
        {
          "question_id": 0,
          "question_type": "정보",
          "question": "연락처가 어떻게 되나요?",
          "question_wordNum": 3,
          "answer": "0507-1379-0415",
          "answer_wordNum": 1,
          "fact": [
            "세라즈피자펍,연락처,0507-1379-0415"
          ]
        },
        {
          "question_id": 1,
          "question_type": "탐색",
          "question": "주차시설이 있나요?",
          "question_wordNum": 2,
          "answer": "있음",
          "answer_wordNum": 1,
          "fact": [
            "세라즈피자펍,주차시설,있음"
          ]
        },
        {
          "question_id": 2,
          "question_type": "정보",
          "question": "이 곳의 주소를 알 수 있나요?",
          "question_wordNum": 6,
          "answer": "서울 금천구 가산디지털1로 168 A동 2층 222호",
          "answer_wordNum": 7,
          "fact": [
            "세라즈피자펍,주소,서울 금천구 가산디지털1로 168 A동 2층 222호"
          ]
        },
        {
          "question_id": 3,
          "question_type": "정보",
          "question": "이 곳의 대표적인 메뉴는 무엇이 있나요?",
          "question_wordNum": 6,
          "answer": "피자, 국내 수제맥주",
          "answer_wordNum": 3,
          "fact": [
            "세라즈피자펍,메뉴,피자, 국내 수제맥주"
          ]
        }
      ]
    },
    {
      "image_id": 4,
      "question": [
        {
          "question_id": 0,
          "question_type": "정보",
          "question": "이 곳의 대표적인 메뉴는 무엇이 있나요?",
          "question_wordNum": 6,
          "answer": "피자, 국내 수제맥주",
          "answer_wordNum": 3,
          "fact": [
            "세라즈피자펍,메뉴,피자, 국내 수제맥주"
          ]
        },
        {
          "question_id": 1,
          "question_type": "정보",
          "question": "영업시간을 알 수 있나요?",
          "question_wordNum": 4,
          "answer": "11:30 - 24:00",
          "answer_wordNum": 3,
          "fact": [
            "세라즈피자펍,영업시간,11:30 - 24:00"
          ]
        },
        {
          "question_id": 2,
          "question_type": "정보",
          "question": "이 곳의 주소를 알 수 있나요?",
          "question_wordNum": 6,
          "answer": "서울 금천구 가산디지털1로 168 A동 2층 222호",
          "answer_wordNum": 7,
          "fact": [
            "세라즈피자펍,주소,서울 금천구 가산디지털1로 168 A동 2층 222호"
          ]
        },
        {
          "question_id": 3,
          "question_type": "탐색",
          "question": "주차시설이 있는지 알 수 있나요?",
          "question_wordNum": 5,
          "answer": "있음",
          "answer_wordNum": 1,
          "fact": [
            "세라즈피자펍,주차시설,있음"
          ]
        }
      ]
    }
  ]
}