{
  "data": {
    "dataset": "2-083-219",
    "POI_id": "562878",
    "travelType": "음식점",
    "place": "연스시  ",
    "area": "서울"
  },
  "imageInfo": [
    {
      "image_id": 0,
      "filename": "562878_0_su_5_연스시  _5_001.png",
      "mapx": 37.5382364927306,
      "mapy": 127.091306726945,
      "width": 3840,
      "height": 2160,
      "caption_info": [
        "연스시(광진구)",
        "간판, 화분, 여닫이문"
      ]
    },
    {
      "image_id": 1,
      "filename": "562878_0_su_5_연스시  _5_002.png",
      "mapx": 37.5382364927306,
      "mapy": 127.091306726945,
      "width": 3840,
      "height": 2160,
      "caption_info": [
        "연스시(광진구)",
        "간판"
      ]
    },
    {
      "image_id": 2,
      "filename": "562878_0_su_5_연스시  _5_003.png",
      "mapx": 37.5382364927306,
      "mapy": 127.091306726945,
      "width": 3840,
      "height": 2160,
      "caption_info": [
        "연스시(광진구)",
        "사각 테이블, 등받이 의자, 액자"
      ]
    },
    {
      "image_id": 3,
      "filename": "562878_0_su_5_연스시  _5_004.png",
      "mapx": 37.5382364927306,
      "mapy": 127.091306726945,
      "width": 3840,
      "height": 2160,
      "caption_info": [
        "연스시(광진구)",
        "메뉴판, 화분"
      ]
    },
    {
      "image_id": 4,
      "filename": "562878_0_su_5_연스시  _5_005.png",
      "mapx": 37.5382364927306,
      "mapy": 127.091306726945,
      "width": 3840,
      "height": 2160,
      "caption_info": [
        "연스시(광진구)",
        "장어"
      ]
    }
  ],
  "annotations": [
    {
      "image_id": 0,
      "question": [
        {
          "question_id": 0,
          "question_type": "관계",
          "question": "이 곳에 인접한 시설이 있나요?",
          "question_wordNum": 5,
          "answer": "구의역 3번 출구, 광진우체국, 구의퓨전빌아파트",
          "answer_wordNum": 5,
          "fact": [
            "연스시,인접,구의역 3번 출구, 광진우체국, 구의퓨전빌아파트"
          ]
        },
        {
          "question_id": 1,
          "question_type": "정보",
          "question": "연락처를 알 수 있나요?",
          "question_wordNum": 4,
          "answer": "0507-1477-0711",
          "answer_wordNum": 1,
          "fact": [
            "연스시,연락처,0507-1477-0711"
          ]
        },
        {
          "question_id": 2,
          "question_type": "탐색",
          "question": "주차시설이 있나요?",
          "question_wordNum": 2,
          "answer": "있음",
          "answer_wordNum": 1,
          "fact": [
            "연스시,주차시설,있음"
          ]
        },
        {
          "question_id": 3,
          "question_type": "정보",
          "question": "휴무일은 어떻게 되나요?",
          "question_wordNum": 3,
          "answer": "알수없음",
          "answer_wordNum": 1,
          "fact": [
            "연스시,휴무일,알수없음"
          ]
        }
      ]
    },
    {
      "image_id": 1,
      "question": [
        {
          "question_id": 0,
          "question_type": "정보",
          "question": "대표 메뉴가 무엇인가요?",
          "question_wordNum": 3,
          "answer": "보리굴비, 계란찜",
          "answer_wordNum": 2,
          "fact": [
            "연스시,메뉴,보리굴비, 계란찜"
          ]
        },
        {
          "question_id": 1,
          "question_type": "탐색",
          "question": "주차시설이 있는지 알 수 있나요?",
          "question_wordNum": 5,
          "answer": "있음",
          "answer_wordNum": 1,
          "fact": [
            "연스시,주차시설,있음"
          ]
        },
        {
          "question_id": 2,
          "question_type": "정보",
          "question": "이 곳의 주소를 알 수 있나요?",
          "question_wordNum": 6,
          "answer": "서울 광진구 아차산로 438 1층",
          "answer_wordNum": 5,
          "fact": [
            "연스시,주소,서울 광진구 아차산로 438 1층"
          ]
        },
        {
          "question_id": 3,
          "question_type": "관계",
          "question": "이 곳에 인접한 시설을 알 수 있나요?",
          "question_wordNum": 7,
          "answer": "구의역 3번 출구, 광진우체국, 구의퓨전빌아파트",
          "answer_wordNum": 5,
          "fact": [
            "연스시,인접,구의역 3번 출구, 광진우체국, 구의퓨전빌아파트"
          ]
        }
      ]
    },
    {
      "image_id": 2,
      "question": [
        {
          "question_id": 0,
          "question_type": "정보",
          "question": "연락처를 알 수 있나요?",
          "question_wordNum": 4,
          "answer": "0507-1477-0711",
          "answer_wordNum": 1,
          "fact": [
            "연스시,연락처,0507-1477-0711"
          ]
        },
        {
          "question_id": 1,
          "question_type": "관계",
          "question": "이 곳에 인접한 시설을 알 수 있나요?",
          "question_wordNum": 7,
          "answer": "구의역 3번 출구, 광진우체국, 구의퓨전빌아파트",
          "answer_wordNum": 5,
          "fact": [
            "연스시,인접,구의역 3번 출구, 광진우체국, 구의퓨전빌아파트"
          ]
        },
        {
          "question_id": 2,
          "question_type": "탐색",
          "question": "주차시설이 있나요?",
          "question_wordNum": 2,
          "answer": "있음",
          "answer_wordNum": 1,
          "fact": [
            "연스시,주차시설,있음"
          ]
        },
        {
          "question_id": 3,
          "question_type": "정보",
          "question": "대표 메뉴가 무엇인가요?",
          "question_wordNum": 3,
          "answer": "보리굴비, 계란찜",
          "answer_wordNum": 2,
          "fact": [
            "연스시,메뉴,보리굴비, 계란찜"
          ]
        }
      ]
    },
    {
      "image_id": 3,
      "question": [
        {
          "question_id": 0,
          "question_type": "정보",
          "question": "이 곳의 주소를 알 수 있나요?",
          "question_wordNum": 6,
          "answer": "서울 광진구 아차산로 438 1층",
          "answer_wordNum": 5,
          "fact": [
            "연스시,주소,서울 광진구 아차산로 438 1층"
          ]
        },
        {
          "question_id": 1,
          "question_type": "탐색",
          "question": "주차시설이 있는지 알 수 있나요?",
          "question_wordNum": 5,
          "answer": "있음",
          "answer_wordNum": 1,
          "fact": [
            "연스시,주차시설,있음"
          ]
        },
        {
          "question_id": 2,
          "question_type": "정보",
          "question": "대표 메뉴가 무엇인가요?",
          "question_wordNum": 3,
          "answer": "보리굴비, 계란찜",
          "answer_wordNum": 2,
          "fact": [
            "연스시,메뉴,보리굴비, 계란찜"
          ]
        },
        {
          "question_id": 3,
          "question_type": "정보",
          "question": "휴무일을 알 수 있나요?",
          "question_wordNum": 4,
          "answer": "알수없음",
          "answer_wordNum": 1,
          "fact": [
            "연스시,휴무일,알수없음"
          ]
        }
      ]
    },
    {
      "image_id": 4,
      "question": [
        {
          "question_id": 0,
          "question_type": "정보",
          "question": "이 곳의 주소를 알 수 있나요?",
          "question_wordNum": 6,
          "answer": "서울 광진구 아차산로 438 1층",
          "answer_wordNum": 5,
          "fact": [
            "연스시,주소,서울 광진구 아차산로 438 1층"
          ]
        },
        {
          "question_id": 1,
          "question_type": "정보",
          "question": "연락처가 어떻게 되나요?",
          "question_wordNum": 3,
          "answer": "0507-1477-0711",
          "answer_wordNum": 1,
          "fact": [
            "연스시,연락처,0507-1477-0711"
          ]
        },
        {
          "question_id": 2,
          "question_type": "탐색",
          "question": "주차시설이 있나요?",
          "question_wordNum": 2,
          "answer": "있음",
          "answer_wordNum": 1,
          "fact": [
            "연스시,주차시설,있음"
          ]
        },
        {
          "question_id": 3,
          "question_type": "정보",
          "question": "휴무일은 어떻게 되나요?",
          "question_wordNum": 3,
          "answer": "알수없음",
          "answer_wordNum": 1,
          "fact": [
            "연스시,휴무일,알수없음"
          ]
        }
      ]
    }
  ]
}