{
  "data": {
    "dataset": "2-083-219",
    "POI_id": "554044",
    "travelType": "음식점",
    "place": "투썸플레이스 도봉산입구점",
    "area": "서울"
  },
  "imageInfo": [
    {
      "image_id": 0,
      "filename": "554044_0_su_5_투썸플레이스 도봉산입구점_1_001.png",
      "mapx": 37.6875992772411,
      "mapy": 127.041667389797,
      "width": 3840,
      "height": 2160,
      "caption_info": [
        "투썸플레이스 도봉산입구점(도봉동)",
        "간판"
      ]
    },
    {
      "image_id": 1,
      "filename": "554044_0_su_5_투썸플레이스 도봉산입구점_1_002.png",
      "mapx": 37.6875992772411,
      "mapy": 127.041667389797,
      "width": 3840,
      "height": 2160,
      "caption_info": [
        "투썸플레이스 도봉산입구점(도봉동)",
        "건물, 간판"
      ]
    },
    {
      "image_id": 2,
      "filename": "554044_0_su_5_투썸플레이스 도봉산입구점_1_003.png",
      "mapx": 37.6875992772411,
      "mapy": 127.041667389797,
      "width": 3840,
      "height": 2160,
      "caption_info": [
        "투썸플레이스 도봉산입구점(도봉동)",
        "테이블, 등받이의자"
      ]
    },
    {
      "image_id": 3,
      "filename": "554044_0_su_5_투썸플레이스 도봉산입구점_1_004.png",
      "mapx": 37.6875992772411,
      "mapy": 127.041667389797,
      "width": 3840,
      "height": 2160,
      "caption_info": [
        "투썸플레이스 도봉산입구점(도봉동)",
        "메뉴판"
      ]
    },
    {
      "image_id": 4,
      "filename": "554044_0_su_5_투썸플레이스 도봉산입구점_1_005.png",
      "mapx": 37.6875992772411,
      "mapy": 127.041667389797,
      "width": 3840,
      "height": 2160,
      "caption_info": [
        "투썸플레이스 도봉산입구점(도봉동)",
        "음료, 조각케이크"
      ]
    }
  ],
  "annotations": [
    {
      "image_id": 0,
      "question": [
        {
          "question_id": 0,
          "question_type": "정보",
          "question": "영업시간은 몇시부터 몇시까지로 기재되어 있나요?",
          "question_wordNum": 5,
          "answer": "09:30-21:30/22:00",
          "answer_wordNum": 1,
          "fact": [
            "투썸플레이스 도봉산입구점,영업시간,09:30-21:30/22:00"
          ]
        },
        {
          "question_id": 1,
          "question_type": "정보",
          "question": "이 곳의 주소가 어떻게 되나요?",
          "question_wordNum": 5,
          "answer": "서울 도봉구 도봉산4가길 13-11",
          "answer_wordNum": 4,
          "fact": [
            "투썸플레이스 도봉산입구점,주소,서울 도봉구 도봉산4가길 13-11"
          ]
        },
        {
          "question_id": 2,
          "question_type": "정보",
          "question": "연락처가 어떻게 되나요?",
          "question_wordNum": 3,
          "answer": "0507-1431-7926",
          "answer_wordNum": 1,
          "fact": [
            "투썸플레이스 도봉산입구점,연락처,0507-1431-7926"
          ]
        },
        {
          "question_id": 3,
          "question_type": "정보",
          "question": "이 곳의 대표적인 메뉴는 무엇이 있나요?",
          "question_wordNum": 6,
          "answer": "아메리카노, 오렌지자몽주스",
          "answer_wordNum": 2,
          "fact": [
            "투썸플레이스 도봉산입구점,메뉴,아메리카노, 오렌지자몽주스"
          ]
        }
      ]
    },
    {
      "image_id": 1,
      "question": [
        {
          "question_id": 0,
          "question_type": "정보",
          "question": "연락처가 어떻게 되나요?",
          "question_wordNum": 3,
          "answer": "0507-1431-7926",
          "answer_wordNum": 1,
          "fact": [
            "투썸플레이스 도봉산입구점,연락처,0507-1431-7926"
          ]
        },
        {
          "question_id": 1,
          "question_type": "정보",
          "question": "이 곳의 주요 메뉴가 어떻게 되나요?",
          "question_wordNum": 6,
          "answer": "아메리카노, 오렌지자몽주스",
          "answer_wordNum": 2,
          "fact": [
            "투썸플레이스 도봉산입구점,메뉴,아메리카노, 오렌지자몽주스"
          ]
        },
        {
          "question_id": 2,
          "question_type": "정보",
          "question": "영업시간은 어떻게 되나요?",
          "question_wordNum": 3,
          "answer": "09:30-21:30/22:00",
          "answer_wordNum": 1,
          "fact": [
            "투썸플레이스 도봉산입구점,영업시간,09:30-21:30/22:00"
          ]
        },
        {
          "question_id": 3,
          "question_type": "관계",
          "question": "이 곳에 인접한 시설이 어떻게 되나요?",
          "question_wordNum": 6,
          "answer": "도봉산역 1번 출구, 통아웃도어, 영원아웃도어 도봉산직영점",
          "answer_wordNum": 6,
          "fact": [
            "투썸플레이스 도봉산입구점,인접,도봉산역 1번 출구, 통아웃도어, 영원아웃도어 도봉산직영점"
          ]
        }
      ]
    },
    {
      "image_id": 2,
      "question": [
        {
          "question_id": 0,
          "question_type": "정보",
          "question": "휴무일은 어떻게 되나요?",
          "question_wordNum": 3,
          "answer": "알수없음",
          "answer_wordNum": 1,
          "fact": [
            "투썸플레이스 도봉산입구점,휴무일,알수없음"
          ]
        },
        {
          "question_id": 1,
          "question_type": "정보",
          "question": "이 곳의 대표적인 메뉴는 무엇이 있나요?",
          "question_wordNum": 6,
          "answer": "아메리카노, 오렌지자몽주스",
          "answer_wordNum": 2,
          "fact": [
            "투썸플레이스 도봉산입구점,메뉴,아메리카노, 오렌지자몽주스"
          ]
        },
        {
          "question_id": 2,
          "question_type": "탐색",
          "question": "주차시설이 있나요?",
          "question_wordNum": 2,
          "answer": "있음",
          "answer_wordNum": 1,
          "fact": [
            "투썸플레이스 도봉산입구점,주차시설,있음"
          ]
        },
        {
          "question_id": 3,
          "question_type": "관계",
          "question": "이 곳에 인접한 시설이 어떻게 되나요?",
          "question_wordNum": 6,
          "answer": "도봉산역 1번 출구, 통아웃도어, 영원아웃도어 도봉산직영점",
          "answer_wordNum": 6,
          "fact": [
            "투썸플레이스 도봉산입구점,인접,도봉산역 1번 출구, 통아웃도어, 영원아웃도어 도봉산직영점"
          ]
        }
      ]
    },
    {
      "image_id": 3,
      "question": [
        {
          "question_id": 0,
          "question_type": "탐색",
          "question": "주차시설이 있나요?",
          "question_wordNum": 2,
          "answer": "있음",
          "answer_wordNum": 1,
          "fact": [
            "투썸플레이스 도봉산입구점,주차시설,있음"
          ]
        },
        {
          "question_id": 1,
          "question_type": "정보",
          "question": "이 곳의 대표적인 메뉴는 무엇이 있나요?",
          "question_wordNum": 6,
          "answer": "아메리카노, 오렌지자몽주스",
          "answer_wordNum": 2,
          "fact": [
            "투썸플레이스 도봉산입구점,메뉴,아메리카노, 오렌지자몽주스"
          ]
        },
        {
          "question_id": 2,
          "question_type": "관계",
          "question": "이 곳에 인접한 시설이 어떻게 되나요?",
          "question_wordNum": 6,
          "answer": "도봉산역 1번 출구, 통아웃도어, 영원아웃도어 도봉산직영점",
          "answer_wordNum": 6,
          "fact": [
            "투썸플레이스 도봉산입구점,인접,도봉산역 1번 출구, 통아웃도어, 영원아웃도어 도봉산직영점"
          ]
        },
        {
          "question_id": 3,
          "question_type": "정보",
          "question": "영업시간은 어떻게 되나요?",
          "question_wordNum": 3,
          "answer": "09:30-21:30/22:00",
          "answer_wordNum": 1,
          "fact": [
            "투썸플레이스 도봉산입구점,영업시간,09:30-21:30/22:00"
          ]
        }
      ]
    },
    {
      "image_id": 4,
      "question": [
        {
          "question_id": 0,
          "question_type": "탐색",
          "question": "주차시설이 있나요?",
          "question_wordNum": 2,
          "answer": "있음",
          "answer_wordNum": 1,
          "fact": [
            "투썸플레이스 도봉산입구점,주차시설,있음"
          ]
        },
        {
          "question_id": 1,
          "question_type": "관계",
          "question": "이 곳에 인접한 시설이 어떻게 되나요?",
          "question_wordNum": 6,
          "answer": "도봉산역 1번 출구, 통아웃도어, 영원아웃도어 도봉산직영점",
          "answer_wordNum": 6,
          "fact": [
            "투썸플레이스 도봉산입구점,인접,도봉산역 1번 출구, 통아웃도어, 영원아웃도어 도봉산직영점"
          ]
        },
        {
          "question_id": 2,
          "question_type": "정보",
          "question": "연락처가 어떻게 되나요?",
          "question_wordNum": 3,
          "answer": "0507-1431-7926",
          "answer_wordNum": 1,
          "fact": [
            "투썸플레이스 도봉산입구점,연락처,0507-1431-7926"
          ]
        },
        {
          "question_id": 3,
          "question_type": "정보",
          "question": "휴무일은 어떻게 되나요?",
          "question_wordNum": 3,
          "answer": "알수없음",
          "answer_wordNum": 1,
          "fact": [
            "투썸플레이스 도봉산입구점,휴무일,알수없음"
          ]
        }
      ]
    }
  ]
}