{
  "data": {
    "dataset": "2-083-219",
    "POI_id": "564043",
    "travelType": "음식점",
    "place": "사랑방손칼국수",
    "area": "서울"
  },
  "imageInfo": [
    {
      "image_id": 0,
      "filename": "564043_0_su_5_사랑방손칼국수_2_001.png",
      "mapx": 37.4966754401074,
      "mapy": 126.857270300757,
      "width": 3840,
      "height": 2160,
      "caption_info": [
        "사랑방손칼국수(개봉동)",
        "간판, 여닫이문"
      ]
    },
    {
      "image_id": 1,
      "filename": "564043_0_su_5_사랑방손칼국수_2_002.png",
      "mapx": 37.4966754401074,
      "mapy": 126.857270300757,
      "width": 3840,
      "height": 2160,
      "caption_info": [
        "사랑방손칼국수(개봉동)",
        "건물, 간판, 전깃줄"
      ]
    },
    {
      "image_id": 2,
      "filename": "564043_0_su_5_사랑방손칼국수_2_003.png",
      "mapx": 37.4966754401074,
      "mapy": 126.857270300757,
      "width": 3840,
      "height": 2160,
      "caption_info": [
        "사랑방손칼국수(개봉동)",
        "테이블, 등받이의자, 시스템에어컨"
      ]
    },
    {
      "image_id": 3,
      "filename": "564043_0_su_5_사랑방손칼국수_2_004.png",
      "mapx": 37.4966754401074,
      "mapy": 126.857270300757,
      "width": 3840,
      "height": 2160,
      "caption_info": [
        "사랑방손칼국수(개봉동)",
        "메뉴판"
      ]
    },
    {
      "image_id": 4,
      "filename": "564043_0_su_5_사랑방손칼국수_2_005.png",
      "mapx": 37.4966754401074,
      "mapy": 126.857270300757,
      "width": 3840,
      "height": 2160,
      "caption_info": [
        "사랑방손칼국수(개봉동)",
        "비빔밥"
      ]
    }
  ],
  "annotations": [
    {
      "image_id": 0,
      "question": [
        {
          "question_id": 0,
          "question_type": "관계",
          "question": "이 곳에 인접한 시설을 알 수 있나요?",
          "question_wordNum": 7,
          "answer": "개봉역 2번 출구, 민물슈퍼마켓, 다채",
          "answer_wordNum": 5,
          "fact": [
            "사랑방손칼국수,인접,개봉역 2번 출구, 민물슈퍼마켓, 다채"
          ]
        },
        {
          "question_id": 1,
          "question_type": "탐색",
          "question": "주차시설이 있나요?",
          "question_wordNum": 2,
          "answer": "있음",
          "answer_wordNum": 1,
          "fact": [
            "사랑방손칼국수,주차시설,있음"
          ]
        },
        {
          "question_id": 2,
          "question_type": "정보",
          "question": "영업시간은 어떻게 되나요?",
          "question_wordNum": 3,
          "answer": "11:30~20:30",
          "answer_wordNum": 1,
          "fact": [
            "사랑방손칼국수,영업시간,11:30~20:30"
          ]
        },
        {
          "question_id": 3,
          "question_type": "정보",
          "question": "이 곳의 주소를 알 수 있나요?",
          "question_wordNum": 6,
          "answer": "서울 구로구 경인로38길 12",
          "answer_wordNum": 4,
          "fact": [
            "사랑방손칼국수,주소,서울 구로구 경인로38길 12"
          ]
        }
      ]
    },
    {
      "image_id": 1,
      "question": [
        {
          "question_id": 0,
          "question_type": "관계",
          "question": "이 곳에 인접한 시설을 알 수 있나요?",
          "question_wordNum": 7,
          "answer": "개봉역 2번 출구, 민물슈퍼마켓, 다채",
          "answer_wordNum": 5,
          "fact": [
            "사랑방손칼국수,인접,개봉역 2번 출구, 민물슈퍼마켓, 다채"
          ]
        },
        {
          "question_id": 1,
          "question_type": "탐색",
          "question": "주차시설이 있는지 알 수 있나요?",
          "question_wordNum": 5,
          "answer": "있음",
          "answer_wordNum": 1,
          "fact": [
            "사랑방손칼국수,주차시설,있음"
          ]
        },
        {
          "question_id": 2,
          "question_type": "정보",
          "question": "휴무일은 어떻게 되나요?",
          "question_wordNum": 3,
          "answer": "매주 일요일",
          "answer_wordNum": 2,
          "fact": [
            "사랑방손칼국수,휴무일,매주 일요일"
          ]
        },
        {
          "question_id": 3,
          "question_type": "정보",
          "question": "연락처를 알 수 있나요?",
          "question_wordNum": 4,
          "answer": "02-3666-6632",
          "answer_wordNum": 1,
          "fact": [
            "사랑방손칼국수,연락처,02-3666-6632"
          ]
        }
      ]
    },
    {
      "image_id": 2,
      "question": [
        {
          "question_id": 0,
          "question_type": "관계",
          "question": "이 곳에 인접한 시설이 있나요?",
          "question_wordNum": 5,
          "answer": "개봉역 2번 출구, 민물슈퍼마켓, 다채",
          "answer_wordNum": 5,
          "fact": [
            "사랑방손칼국수,인접,개봉역 2번 출구, 민물슈퍼마켓, 다채"
          ]
        },
        {
          "question_id": 1,
          "question_type": "정보",
          "question": "연락처를 알 수 있나요?",
          "question_wordNum": 4,
          "answer": "02-3666-6632",
          "answer_wordNum": 1,
          "fact": [
            "사랑방손칼국수,연락처,02-3666-6632"
          ]
        },
        {
          "question_id": 2,
          "question_type": "정보",
          "question": "영업시간은 어떻게 되나요?",
          "question_wordNum": 3,
          "answer": "11:30~20:30",
          "answer_wordNum": 1,
          "fact": [
            "사랑방손칼국수,영업시간,11:30~20:30"
          ]
        },
        {
          "question_id": 3,
          "question_type": "정보",
          "question": "이 곳의 주요 메뉴를 알 수 있나요?",
          "question_wordNum": 7,
          "answer": "칼국수, 물막국수",
          "answer_wordNum": 2,
          "fact": [
            "사랑방손칼국수,메뉴,칼국수, 물막국수"
          ]
        }
      ]
    },
    {
      "image_id": 3,
      "question": [
        {
          "question_id": 0,
          "question_type": "정보",
          "question": "이 곳의 대표적인 메뉴는 무엇이 있나요?",
          "question_wordNum": 6,
          "answer": "칼국수, 물막국수",
          "answer_wordNum": 2,
          "fact": [
            "사랑방손칼국수,메뉴,칼국수, 물막국수"
          ]
        },
        {
          "question_id": 1,
          "question_type": "정보",
          "question": "휴무일을 알 수 있나요?",
          "question_wordNum": 4,
          "answer": "매주 일요일",
          "answer_wordNum": 2,
          "fact": [
            "사랑방손칼국수,휴무일,매주 일요일"
          ]
        },
        {
          "question_id": 2,
          "question_type": "정보",
          "question": "영업시간은 어떻게 되나요?",
          "question_wordNum": 3,
          "answer": "11:30~20:30",
          "answer_wordNum": 1,
          "fact": [
            "사랑방손칼국수,영업시간,11:30~20:30"
          ]
        },
        {
          "question_id": 3,
          "question_type": "탐색",
          "question": "주차시설이 있나요?",
          "question_wordNum": 2,
          "answer": "있음",
          "answer_wordNum": 1,
          "fact": [
            "사랑방손칼국수,주차시설,있음"
          ]
        }
      ]
    },
    {
      "image_id": 4,
      "question": [
        {
          "question_id": 0,
          "question_type": "관계",
          "question": "이 곳에 인접한 시설을 알 수 있나요?",
          "question_wordNum": 7,
          "answer": "개봉역 2번 출구, 민물슈퍼마켓, 다채",
          "answer_wordNum": 5,
          "fact": [
            "사랑방손칼국수,인접,개봉역 2번 출구, 민물슈퍼마켓, 다채"
          ]
        },
        {
          "question_id": 1,
          "question_type": "정보",
          "question": "연락처가 어떻게 되나요?",
          "question_wordNum": 3,
          "answer": "02-3666-6632",
          "answer_wordNum": 1,
          "fact": [
            "사랑방손칼국수,연락처,02-3666-6632"
          ]
        },
        {
          "question_id": 2,
          "question_type": "정보",
          "question": "영업시간을 알 수 있나요?",
          "question_wordNum": 4,
          "answer": "11:30~20:30",
          "answer_wordNum": 1,
          "fact": [
            "사랑방손칼국수,영업시간,11:30~20:30"
          ]
        },
        {
          "question_id": 3,
          "question_type": "정보",
          "question": "휴무일은 어떻게 되나요?",
          "question_wordNum": 3,
          "answer": "매주 일요일",
          "answer_wordNum": 2,
          "fact": [
            "사랑방손칼국수,휴무일,매주 일요일"
          ]
        }
      ]
    }
  ]
}